subsurface/__init__.py
subsurface/_version.py
subsurface/optional_requirements.py
subsurface/api/__init__.py
subsurface/api/interfaces/__init__.py
subsurface/api/interfaces/stream.py
subsurface/core/__init__.py
subsurface/core/geological_formats/__init__.py
subsurface/core/geological_formats/fault.py
subsurface/core/geological_formats/boreholes/__init__.py
subsurface/core/geological_formats/boreholes/_combine_trajectories.py
subsurface/core/geological_formats/boreholes/boreholes.py
subsurface/core/geological_formats/boreholes/collars.py
subsurface/core/geological_formats/boreholes/survey.py
subsurface/core/reader_helpers/__init__.py
subsurface/core/reader_helpers/reader_unstruct.py
subsurface/core/reader_helpers/readers_data.py
subsurface/core/reader_helpers/readers_wells.py
subsurface/core/structs/__init__.py
subsurface/core/structs/base_structures/__init__.py
subsurface/core/structs/base_structures/_unstructured_data_constructor.py
subsurface/core/structs/base_structures/base_structures_enum.py
subsurface/core/structs/base_structures/structured_data.py
subsurface/core/structs/base_structures/unstructured_data.py
subsurface/core/structs/structured_elements/__init__.py
subsurface/core/structs/structured_elements/octree_mesh.py
subsurface/core/structs/structured_elements/structured_grid.py
subsurface/core/structs/structured_elements/structured_mesh.py
subsurface/core/structs/unstructured_elements/__init__.py
subsurface/core/structs/unstructured_elements/line_set.py
subsurface/core/structs/unstructured_elements/point_set.py
subsurface/core/structs/unstructured_elements/tetrahedron_mesh.py
subsurface/core/structs/unstructured_elements/triangular_surface.py
subsurface/core/utils/__init__.py
subsurface/core/utils/utils_core.py
subsurface/modules/__init__.py
subsurface/modules/reader/__init__.py
subsurface/modules/reader/from_binary.py
subsurface/modules/reader/read_netcdf.py
subsurface/modules/reader/faults/__init__.py
subsurface/modules/reader/faults/faults.py
subsurface-2024.2.2.dist-info/LICENSE
subsurface-2024.2.2.dist-info/METADATA
subsurface-2024.2.2.dist-info/WHEEL
subsurface-2024.2.2.dist-info/top_level.txt
subsurface-2024.2.2.dist-info/RECORD
