Metadata-Version: 2.1
Name: subsurface
Version: 2024.2.2
Summary: Subsurface data types and utilities
Home-page: https://softwareunderground.github.io/subsurface
Author: Software Underground
Author-email: hello@softwareunderground.org
License: Apache-2.0
Classifier: Development Status :: 3 - Alpha
Classifier: Intended Audience :: Science/Research
Classifier: Natural Language :: English
Classifier: License :: OSI Approved :: Apache Software License
Classifier: Operating System :: OS Independent
License-File: LICENSE
Requires-Dist: xarray
Requires-Dist: netcdf4
Requires-Dist: python-dotenv
Provides-Extra: all
Requires-Dist: xarray ; extra == 'all'
Requires-Dist: netcdf4 ; extra == 'all'
Requires-Dist: python-dotenv ; extra == 'all'
Requires-Dist: matplotlib ; extra == 'all'
Requires-Dist: pyvista ; extra == 'all'
Requires-Dist: ezdxf ; extra == 'all'
Requires-Dist: trimesh ; extra == 'all'
Requires-Dist: networkx ; extra == 'all'
Requires-Dist: imageio ; extra == 'all'
Requires-Dist: omfvista ; extra == 'all'
Requires-Dist: segyio ; extra == 'all'
Requires-Dist: scipy ; extra == 'all'
Requires-Dist: geopandas ; extra == 'all'
Requires-Dist: rasterio ; extra == 'all'
Requires-Dist: numpy ; extra == 'all'
Requires-Dist: pandas ; extra == 'all'
Requires-Dist: sphinx ~=3.5 ; extra == 'all'
Requires-Dist: sphinx-gallery ; extra == 'all'
Requires-Dist: sphinx-rtd-theme ; extra == 'all'
Requires-Dist: sphinx-automodapi ; extra == 'all'
Requires-Dist: pytest ; extra == 'all'
Requires-Dist: pytest-cov ; extra == 'all'
Provides-Extra: dev
Requires-Dist: xarray ; extra == 'dev'
Requires-Dist: netcdf4 ; extra == 'dev'
Requires-Dist: python-dotenv ; extra == 'dev'
Requires-Dist: numpy ; extra == 'dev'
Requires-Dist: pandas ; extra == 'dev'
Requires-Dist: sphinx ~=3.5 ; extra == 'dev'
Requires-Dist: sphinx-gallery ; extra == 'dev'
Requires-Dist: sphinx-rtd-theme ; extra == 'dev'
Requires-Dist: sphinx-automodapi ; extra == 'dev'
Requires-Dist: pytest ; extra == 'dev'
Requires-Dist: pytest-cov ; extra == 'dev'
Provides-Extra: opt
Requires-Dist: xarray ; extra == 'opt'
Requires-Dist: netcdf4 ; extra == 'opt'
Requires-Dist: python-dotenv ; extra == 'opt'
Requires-Dist: matplotlib ; extra == 'opt'
Requires-Dist: pyvista ; extra == 'opt'
Requires-Dist: ezdxf ; extra == 'opt'
Requires-Dist: trimesh ; extra == 'opt'
Requires-Dist: networkx ; extra == 'opt'
Requires-Dist: imageio ; extra == 'opt'
Requires-Dist: omfvista ; extra == 'opt'
Requires-Dist: segyio ; extra == 'opt'
Requires-Dist: scipy ; extra == 'opt'
Requires-Dist: geopandas ; extra == 'opt'
Requires-Dist: pooch ; extra == 'opt'
Provides-Extra: plog
Requires-Dist: xarray ; extra == 'plog'
Requires-Dist: netcdf4 ; extra == 'plog'
Requires-Dist: python-dotenv ; extra == 'plog'
Requires-Dist: matplotlib ; extra == 'plog'
Requires-Dist: pyvista ; extra == 'plog'
